README.md
setup.py
devrant_dl/__init__.py
devrant_dl/__main__.py
devrant_dl/api.py
devrant_dl/files.py
devrant_dl/structures.py
devrant_dl.egg-info/PKG-INFO
devrant_dl.egg-info/SOURCES.txt
devrant_dl.egg-info/dependency_links.txt
devrant_dl.egg-info/entry_points.txt
devrant_dl.egg-info/top_level.txt