Metadata-Version: 2.1
Name: devrant-dl
Version: 1.0.0
Summary: Get a dump of your entire history on devRant
Home-page: https://github.com/Ewpratten/devrant-dl
Author: Evan Pratten
Author-email: ewpratten@gmail.com
License: UNKNOWN
Platform: UNKNOWN
Classifier: Programming Language :: Python :: 3
Classifier: Operating System :: OS Independent
Classifier: Development Status :: 5 - Production/Stable
